{"header":"PROCESSED on Mon, 22 Nov 2021 09:18:20 +0000 from https:\/\/clients.fivehosting.net\/notre-base-de-connaissance-et-tutoriel-divers","files":{"woocommerce-general":{"url":"\/wp-content\/plugins\/woocommerce\/assets\/css\/woocommerce.css","success":true},"wp-optimize-global":{"url":"\/wp-content\/plugins\/wp-optimize\/css\/wp-optimize-global-3-1-12.min.css","success":true},"bootstrap":{"url":"\/wp-content\/themes\/phox\/assets\/css\/bootstrap.min.css","success":true},"wdes-style":{"url":"\/wp-content\/themes\/phox\/assets\/css\/style.css","success":true},"child-style":{"url":"\/wp-content\/themes\/phox-child\/style.css","success":true},"elementor-icons-shared-0-css":{"url":"\/wp-content\/themes\/phox\/assets\/css\/all.min.css","success":true},"wdes-woocommerce":{"url":"\/wp-content\/themes\/phox\/assets\/css\/pages\/dist\/woocommerce.css","success":true},"wdes-responsive":{"url":"\/wp-content\/themes\/phox\/assets\/css\/responsive.css","success":true},"wpforms-admin-bar":{"url":"\/wp-content\/plugins\/wpforms-lite\/assets\/css\/admin-bar.min.css","success":true}}}